{
  "metadata": {
    "questionId": "Q002",
    "project": "政府/國網中心-AI服務",
    "version": "v2",
    "model": "mistralai/ministral-14b-2512",
    "mode": "有上網",
    "scoredBy": "opus",
    "scoredAt": "2026-01-31T12:00:00+08:00"
  },
  "波特人評分": {
    "真": {
      "score": 8,
      "max": 10,
      "weight": 2.5,
      "weighted": 20.0,
      "reason": "正確引用大南方新矽谷推動方案、晶片驅動產業創新方案等政府計畫，提到國網雲端算力中心（台南南科）2025年啟用、沙崙算力中心等具體資訊。480PF組成說明清楚，但部分細節如「470PF」沙崙中心數字略有差異。有附上新聞來源連結。"
    },
    "人": {
      "score": 9,
      "max": 10,
      "weight": 1.5,
      "weighted": 13.5,
      "reason": "回答結構清晰，依序回答四個子問題，使用表格摘要計畫資訊，便於資訊長向部長報告。提供具體申請管道與建議。"
    },
    "準": {
      "score": 8,
      "max": 10,
      "weight": 1.5,
      "weighted": 12.0,
      "reason": "專業術語使用正確（PF、GPU、H200等），計畫名稱與時程說明精確。政府與民間算力比例（40%:60%）說明清楚。"
    },
    "全": {
      "score": 9,
      "max": 10,
      "weight": 1.5,
      "weighted": 13.5,
      "reason": "完整回答480PF組成、目前進度、1200+PF目標、跨部會協調四個問題，並從政府算力規劃、計畫進度、跨部會協調三面向說明。"
    },
    "新": {
      "score": 7,
      "max": 10,
      "weight": 1.0,
      "weighted": 7.0,
      "reason": "提到臺灣算力聯盟等較新資訊，並整合多個來源形成完整藍圖，具有一定整合創新價值。"
    },
    "安": {
      "score": 9,
      "max": 10,
      "weight": 0.8,
      "weighted": 7.2,
      "reason": "建議合規，指引正確的申請管道，無誤導性資訊。"
    },
    "穩": {
      "score": 9,
      "max": 10,
      "weight": 0.5,
      "weighted": 4.5,
      "reason": "邏輯結構嚴謹，從計畫組成到進度到申請方式，層層遞進。"
    },
    "快": {
      "score": 7,
      "max": 10,
      "weight": 0.4,
      "weighted": 2.8,
      "reason": "重點明確，但篇幅較長，部分內容可更精煉。"
    },
    "省": {
      "score": 5,
      "max": 10,
      "weight": 0.3,
      "weighted": 1.5,
      "reason": "回答超過 3500 字，內容詳盡但略顯冗長。"
    }
  },
  "總分": 82.0,
  "滿分": 100,
  "等級": "進階級",
  "analysis": {
    "strengths": [
      "正確引用政府計畫名稱與時程",
      "完整回答四個子問題，結構清晰",
      "提供具體申請管道與對接建議"
    ],
    "weaknesses": [
      "回答篇幅較長，可更精煉",
      "部分算力數字細節可能因時間差異略有出入"
    ],
    "summary": "對政府算力規劃有深入理解，引用正確且完整。結構清晰便於向上報告，達進階水準。"
  }
}
